README
setup.py
odslib/__init__.py
odslib/odsContent.py
odslib/odsManifest.py
odslib/odsMeta.py
odslib/odsMimetype.py
odslib/odsSettings.py
odslib/odsStyles.py
odslib/odsXML.py
odslib.egg-info/PKG-INFO
odslib.egg-info/SOURCES.txt
odslib.egg-info/dependency_links.txt
odslib.egg-info/top_level.txt