Metadata-Version: 1.1
Name: odslib
Version: 1.0.2
Summary: An easy to use module that creates ODS documents. Fork of original odslib-python (http://code.google.com/p/odslib-python/). Original author: Joseph Colton
Home-page: https://bitbucket.org/angry_elf/odslib/
Author: Alexey Loshkarev
Author-email: elf2001@gmail.com
License: GPL
Platform: UNKNOWN
Classifier: Development Status :: 5 - Production/Stable
Classifier: Intended Audience :: Developers
Classifier: License :: OSI Approved :: GNU General Public License (GPL)
Classifier: Natural Language :: English
Classifier: Programming Language :: Python
Classifier: Topic :: Software Development :: Libraries :: Python Modules
